{"stats":{"minecraft:used":{"minecraft:cooked_mutton":8,"minecraft:stone_pickaxe":41,"minecraft:ladder":1,"minecraft:wooden_pickaxe":4,"minecraft:mossy_cobblestone":1,"minecraft:crafting_table":4,"minecraft:white_bed":1,"minecraft:apple":1,"cure:vaccine":1,"marbledsmelees:fire_axe":250,"minecraft:iron_axe":8,"minecraft:bread":8,"minecraft:iron_pickaxe":3,"minecraft:iron_helmet":1,"minecraft:iron_boots":1,"minecraft:cobblestone":6,"minecraft:furnace":1,"minecraft:oak_boat":2,"minecraft:acacia_planks":1},"minecraft:killed":{"minecraft:husk":2,"minecraft:pig":3,"minecraft:zombie_villager":1,"alexsmobs:raccoon":1,"alexsmobs:seagull":1,"minecraft:sheep":8,"minecraft:zombie":33,"minecraft:player":1,"minecraft:cow":4},"minecraft:killed_by":{"minecraft:husk":1,"minecraft:player":1,"minecraft:zombie":5},"minecraft:broken":{"marbledsmelees:fire_axe":1},"minecraft:dropped":{"minecraft:moss_block":1,"alexsmobs:acacia_blossom":1,"minecraft:rotten_flesh":6,"minecraft:cooked_mutton":2,"minecraft:copper_ingot":2,"minecraft:stick":10,"minecraft:potato":1,"minecraft:acacia_sapling":2,"minecraft:stone_pickaxe":1,"alexsmobs:raccoon_tail":1},"minecraft:crafted":{"minecraft:oak_planks":32,"minecraft:crafting_table":3,"minecraft:wooden_pickaxe":1,"minecraft:furnace":1,"minecraft:cooked_mutton":8,"minecraft:air":0,"minecraft:oak_boat":2,"minecraft:iron_axe":1,"minecraft:stick":12,"minecraft:iron_pickaxe":1,"minecraft:stone_pickaxe":1,"minecraft:white_bed":1,"minecraft:acacia_planks":32},"minecraft:custom":{"minecraft:interact_with_smithing_table":1,"minecraft:interact_with_furnace":3,"lootr:looted_stat":17,"minecraft:mob_kills":53,"minecraft:interact_with_crafting_table":10,"mobcontrol:player_days":3,"minecraft:damage_dealt_resisted":0,"minecraft:leave_game":3,"minecraft:time_since_death":9578,"minecraft:sleep_in_bed":1,"minecraft:climb_one_cm":42366,"minecraft:damage_resisted":0,"minecraft:time_since_rest":9601,"minecraft:sprint_one_cm":381318,"minecraft:damage_absorbed":113,"minecraft:damage_taken":3117,"minecraft:walk_one_cm":286967,"minecraft:drop":14,"mobcontrol:player_ticks":20982,"minecraft:damage_dealt":10064,"minecraft:damage_dealt_absorbed":80,"minecraft:player_kills":1,"minecraft:swim_one_cm":52680,"minecraft:fly_one_cm":367555,"minecraft:open_chest":5,"minecraft:crouch_one_cm":1344,"minecraft:play_time":93513,"minecraft:deaths":9,"minecraft:sneak_time":1182,"minecraft:walk_under_water_one_cm":18597,"minecraft:boat_one_cm":145151,"minecraft:jump":1346,"minecraft:walk_on_water_one_cm":29872,"minecraft:total_world_time":93513,"minecraft:fall_one_cm":36608},"minecraft:picked_up":{"minecraft:crafting_table":2,"minecraft:ladder":2,"alexsmobs:acacia_blossom":1,"minecraft:potato":1,"immersive_weathering:exposed_iron_bars":2,"minecraft:lily_pad":2,"minecraft:oak_log":8,"cure:vaccine":2,"minecraft:gunpowder":5,"minecraft:cooked_mutton":2,"minecraft:bone":8,"minecraft:acacia_planks":2,"minecraft:apple":1,"minecraft:wheat_seeds":2,"minecraft:iron_ingot":2,"minecraft:beef":12,"alexsmobs:raccoon_tail":1,"minecraft:iron_nugget":12,"minecraft:light_gray_wool":2,"minecraft:moss_block":4,"minecraft:acacia_sapling":7,"immersive_weathering:tallow":3,"minecraft:stick":16,"minecraft:copper_ingot":5,"minecraft:torch":1,"minecraft:acacia_log":8,"minecraft:porkchop":5,"pointblank:gunmetal_nugget":45,"minecraft:carrot":1,"bloomingnature:prickly_pear_cactus":1,"minecraft:spider_eye":2,"minecraft:mossy_cobblestone":2,"minecraft:rotten_flesh":43,"minecraft:slime_ball":2,"projectvibrantjourneys:cattail":4,"minecraft:bread":3,"minecraft:oak_sapling":8,"minecraft:black_wool":1,"minecraft:mutton":13,"minecraft:coal":12,"minecraft:white_wool":5,"minecraft:cobblestone":21},"minecraft:mined":{"immersive_weathering:stone_wall":1,"projectvibrantjourneys:cattail":4,"immersive_weathering:exposed_iron_bars":1,"minecraft:crafting_table":2,"minecraft:acacia_log":8,"minecraft:white_stained_glass_pane":7,"minecraft:tall_grass":2,"minecraft:moss_block":2,"minecraft:spawner":2,"minecraft:large_fern":2,"minecraft:seagrass":1,"immersive_weathering:mossy_stone":2,"minecraft:azure_bluet":1,"minecraft:grass":7,"minecraft:oak_log":8,"minecraft:coal_ore":13,"bloomingnature:prickly_pear_cactus":1,"minecraft:acacia_planks":1,"minecraft:stone":22,"minecraft:oak_leaves":2}},"DataVersion":3465}